{"_default": {"1": {"Status": "New", "DueDate": "5/12/18", "Category": "Work", "Description": "Send that Email"}, "2": {"Status": "New", "DueDate": "5/11/18", "Category": "Home", "Description": "Do the Laundry"}, "3": {"Status": "New", "DueDate": "5/11/18", "Category": "Home", "Description": "Do the Dishes"}, "4": {"Status": "New", "DueDate": "5/14/18", "Category": "Work", "Description": "Request a Promotion"}, "5": {"Status": "New", "DueDate": "5/12/18", "Category": "Work", "Description": "Send that Email"}, "6": {"Status": "New", "DueDate": "5/11/18", "Category": "Home", "Description": "Do the Laundry"}, "7": {"Status": "New", "DueDate": "5/11/18", "Category": "Home", "Description": "Do the Dishes"}, "8": {"Status": "New", "DueDate": "5/14/18", "Category": "Work", "Description": "Request a Promotion"}, "9": {"Status": "New", "DueDate": "5/12/18", "Category": "Work", "Description": "Send that Email"}, "10": {"Status": "New", "DueDate": "5/11/18", "Category": "Home", "Description": "Do the Laundry"}, "11": {"Status": "New", "DueDate": "5/11/18", "Category": "Home", "Description": "Do the Dishes"}, "12": {"Status": "New", "DueDate": "5/14/18", "Category": "Work", "Description": "Request a Promotion"}, "13": {"Status": "New", "DueDate": "5/12/18", "Category": "Work", "Description": "Send that Email"}, "14": {"Status": "New", "DueDate": "5/11/18", "Category": "Home", "Description": "Do the Laundry"}, "15": {"Status": "New", "DueDate": "5/11/18", "Category": "Home", "Description": "Do the Dishes"}, "16": {"Status": "New", "DueDate": "5/14/18", "Category": "Work", "Description": "Request a Promotion"}, "17": {"Status": "New", "DueDate": "5/12/18", "Category": "Work", "Description": "Send that Email"}, "18": {"Status": "New", "DueDate": "5/11/18", "Category": "Home", "Description": "Do the Laundry"}, "19": {"Status": "New", "DueDate": "5/11/18", "Category": "Home", "Description": "Do the Dishes"}, "20": {"Status": "New", "DueDate": "5/14/18", "Category": "Work", "Description": "Request a Promotion"}, "21": {"Status": "New", "DueDate": "5/12/18", "Category": "Work", "Description": "Send that Email"}, "22": {"Status": "New", "DueDate": "5/11/18", "Category": "Home", "Description": "Do the Laundry"}, "23": {"Status": "New", "DueDate": "5/11/18", "Category": "Home", "Description": "Do the Dishes"}, "24": {"Status": "New", "DueDate": "5/14/18", "Category": "Work", "Description": "Request a Promotion"}, "25": {"Status": "New", "DueDate": "5/12/18", "Category": "Work", "Description": "Send that Email"}, "26": {"Status": "New", "DueDate": "5/11/18", "Category": "Home", "Description": "Do the Laundry"}, "27": {"Status": "New", "DueDate": "5/11/18", "Category": "Home", "Description": "Do the Dishes"}, "28": {"Status": "New", "DueDate": "5/14/18", "Category": "Work", "Description": "Request a Promotion"}, "29": {"Status": "New", "DueDate": "5/12/18", "Category": "Work", "Description": "Send that Email"}, "30": {"Status": "New", "DueDate": "5/11/18", "Category": "Home", "Description": "Do the Laundry"}, "31": {"Status": "New", "DueDate": "5/11/18", "Category": "Home", "Description": "Do the Dishes"}, "32": {"Status": "New", "DueDate": "5/14/18", "Category": "Work", "Description": "Request a Promotion"}, "33": {"Status": "New", "DueDate": "5/12/18", "Category": "Work", "Description": "Send that Email"}, "34": {"Status": "New", "DueDate": "5/11/18", "Category": "Home", "Description": "Do the Laundry"}, "35": {"Status": "New", "DueDate": "5/11/18", "Category": "Home", "Description": "Do the Dishes"}, "36": {"Status": "New", "DueDate": "5/14/18", "Category": "Work", "Description": "Request a Promotion"}}}